deep500/__init__.py
deep500/datasets/__init__.py
deep500/datasets/cifar.py
deep500/datasets/mnist.py
deep500/frameworks/__init__.py
deep500/frameworks/caffe2/__init__.py
deep500/frameworks/caffe2/caffe2_distributed_optimizer.py
deep500/frameworks/caffe2/caffe2_graph_executor.py
deep500/frameworks/caffe2/caffe2_network.py
deep500/frameworks/caffe2/caffe2_visitor_impl.py
deep500/frameworks/caffe2/op_validation.py
deep500/frameworks/caffe2/support/CMakeLists.txt
deep500/frameworks/caffe2/support/mpi_operations.cc
deep500/frameworks/caffe2/support/mpi_operations.h
deep500/frameworks/pytorch/__init__.py
deep500/frameworks/pytorch/op_validation.py
deep500/frameworks/pytorch/pytorch_graph_executor.py
deep500/frameworks/pytorch/pytorch_network.py
deep500/frameworks/pytorch/pytorch_visitor.py
deep500/frameworks/pytorch/custom_operators/CMakeLists.txt
deep500/frameworks/pytorch/custom_operators/__init__.py
deep500/frameworks/pytorch/custom_operators/pytorch.py
deep500/frameworks/pytorch/custom_operators/pytorch.tmpl - Copy.cpp
deep500/frameworks/pytorch/custom_operators/pytorch.tmpl.cpp
deep500/frameworks/reference/__init__.py
deep500/frameworks/reference/distributed_optimizers.py
deep500/frameworks/reference/optimizers.py
deep500/frameworks/reference/reference_build_graph_visitor_impl.py
deep500/frameworks/reference/reference_build_graph_visitor_impl_cpp.py
deep500/frameworks/reference/reference_graph_executor.py
deep500/frameworks/reference/reference_network.py
deep500/frameworks/reference/custom_operators/CMakeLists.txt
deep500/frameworks/reference/custom_operators/__init__.py
deep500/frameworks/reference/custom_operators/base.py
deep500/frameworks/reference/custom_operators/base.tmpl.cpp
deep500/frameworks/reference/custom_operators/custom_op_cpp.py
deep500/frameworks/reference/custom_operators/custom_op_python.py
deep500/frameworks/reference/custom_operators/cpp/operators/add_op.cpp
deep500/frameworks/reference/custom_operators/cpp/operators/averagepool_op.cpp
deep500-0.2.0.dist-info/LICENSE
deep500-0.2.0.dist-info/METADATA
deep500-0.2.0.dist-info/WHEEL
deep500-0.2.0.dist-info/top_level.txt
deep500-0.2.0.dist-info/RECORD
