Metadata-Version: 2.1
Name: deep500
Version: 0.2.0
Summary: The deep learning metaframework
Home-page: https://github.com/deep500/deep500
Author: SPCL @ ETH Zurich
Author-email: talbn@inf.ethz.ch
License: UNKNOWN
Platform: UNKNOWN
Classifier: Programming Language :: Python :: 3.5
Classifier: Programming Language :: Python :: 3.6
Classifier: Programming Language :: Python :: 3.7
Classifier: Programming Language :: Python :: 3.8
Classifier: License :: OSI Approved :: BSD License
Classifier: Operating System :: OS Independent
Requires-Dist: onnx
Requires-Dist: numpy
Requires-Dist: tqdm
Requires-Dist: cmake
